{
    "zips_geo_data": {
        "zip_name": "56157",
        "areas": [
            {
                "coordinates": [
                    {
                        "x": "-96.048723",
                        "y": "44.429677",
                        "z": "0.0"
                    },
                    {
                        "x": "-96.048742",
                        "y": "44.421759",
                        "z": "0.0"
                    },
                    {
                        "x": "-96.039339",
                        "y": "44.421819",
                        "z": "0.0"
                    },
                    {
                        "x": "-96.0393",
                        "y": "44.41515",
                        "z": "0.0"
                    },
                    {
                        "x": "-96.01887",
                        "y": "44.41489",
                        "z": "0.0"
                    },
                    {
                        "x": "-96.01902",
                        "y": "44.39306",
                        "z": "0.0"
                    },
                    {
                        "x": "-95.99858",
                        "y": "44.39286",
                        "z": "0.0"
                    },
                    {
                        "x": "-95.99857",
                        "y": "44.37103",
                        "z": "0.0"
                    },
                    {
                        "x": "-95.95798",
                        "y": "44.37074",
                        "z": "0.0"
                    },
                    {
                        "x": "-95.958016",
                        "y": "44.326936",
                        "z": "0.0"
                    },
                    {
                        "x": "-95.93746",
                        "y": "44.32684",
                        "z": "0.0"
                    },
                    {
                        "x": "-95.937458",
                        "y": "44.322806",
                        "z": "0.0"
                    },
                    {
                        "x": "-95.932491",
                        "y": "44.32468",
                        "z": "0.0"
                    },
                    {
                        "x": "-95.923996",
                        "y": "44.333714",
                        "z": "0.0"
                    },
                    {
                        "x": "-95.922436",
                        "y": "44.336075",
                        "z": "0.0"
                    },
                    {
                        "x": "-95.923089",
                        "y": "44.339879",
                        "z": "0.0"
                    },
                    {
                        "x": "-95.91924",
                        "y": "44.34106",
                        "z": "0.0"
                    },
                    {
                        "x": "-95.8969",
                        "y": "44.34105",
                        "z": "0.0"
                    },
                    {
                        "x": "-95.89704",
                        "y": "44.35558",
                        "z": "0.0"
                    },
                    {
                        "x": "-95.8567",
                        "y": "44.35549",
                        "z": "0.0"
                    },
                    {
                        "x": "-95.85711",
                        "y": "44.41129",
                        "z": "0.0"
                    },
                    {
                        "x": "-95.859852",
                        "y": "44.408879",
                        "z": "0.0"
                    },
                    {
                        "x": "-95.86025",
                        "y": "44.40965",
                        "z": "0.0"
                    },
                    {
                        "x": "-95.858519",
                        "y": "44.4117",
                        "z": "0.0"
                    },
                    {
                        "x": "-95.860314",
                        "y": "44.412714",
                        "z": "0.0"
                    },
                    {
                        "x": "-95.862476",
                        "y": "44.412297",
                        "z": "0.0"
                    },
                    {
                        "x": "-95.862653",
                        "y": "44.411364",
                        "z": "0.0"
                    },
                    {
                        "x": "-95.866177",
                        "y": "44.410675",
                        "z": "0.0"
                    },
                    {
                        "x": "-95.867775",
                        "y": "44.409386",
                        "z": "0.0"
                    },
                    {
                        "x": "-95.87175",
                        "y": "44.410436",
                        "z": "0.0"
                    },
                    {
                        "x": "-95.871742",
                        "y": "44.406811",
                        "z": "0.0"
                    },
                    {
                        "x": "-95.87689",
                        "y": "44.406828",
                        "z": "0.0"
                    },
                    {
                        "x": "-95.87681",
                        "y": "44.41407",
                        "z": "0.0"
                    },
                    {
                        "x": "-95.93781",
                        "y": "44.41435",
                        "z": "0.0"
                    },
                    {
                        "x": "-95.93794",
                        "y": "44.43796",
                        "z": "0.0"
                    },
                    {
                        "x": "-95.940196",
                        "y": "44.436851",
                        "z": "0.0"
                    },
                    {
                        "x": "-95.939715",
                        "y": "44.434577",
                        "z": "0.0"
                    },
                    {
                        "x": "-95.940986",
                        "y": "44.432817",
                        "z": "0.0"
                    },
                    {
                        "x": "-95.94327",
                        "y": "44.434169",
                        "z": "0.0"
                    },
                    {
                        "x": "-95.943006",
                        "y": "44.432715",
                        "z": "0.0"
                    },
                    {
                        "x": "-95.943955",
                        "y": "44.431853",
                        "z": "0.0"
                    },
                    {
                        "x": "-95.945416",
                        "y": "44.43193",
                        "z": "0.0"
                    },
                    {
                        "x": "-95.94641",
                        "y": "44.430268",
                        "z": "0.0"
                    },
                    {
                        "x": "-95.947459",
                        "y": "44.429922",
                        "z": "0.0"
                    },
                    {
                        "x": "-95.946292",
                        "y": "44.427874",
                        "z": "0.0"
                    },
                    {
                        "x": "-95.9471",
                        "y": "44.427273",
                        "z": "0.0"
                    },
                    {
                        "x": "-95.949745",
                        "y": "44.427978",
                        "z": "0.0"
                    },
                    {
                        "x": "-95.950915",
                        "y": "44.426339",
                        "z": "0.0"
                    },
                    {
                        "x": "-95.95337",
                        "y": "44.42551",
                        "z": "0.0"
                    },
                    {
                        "x": "-95.95811",
                        "y": "44.42498",
                        "z": "0.0"
                    },
                    {
                        "x": "-95.95838",
                        "y": "44.45807",
                        "z": "0.0"
                    },
                    {
                        "x": "-96.029124",
                        "y": "44.458513",
                        "z": "0.0"
                    },
                    {
                        "x": "-96.029152",
                        "y": "44.451101",
                        "z": "0.0"
                    },
                    {
                        "x": "-96.03385",
                        "y": "44.451097",
                        "z": "0.0"
                    },
                    {
                        "x": "-96.03385",
                        "y": "44.444155",
                        "z": "0.0"
                    },
                    {
                        "x": "-96.03954",
                        "y": "44.44421",
                        "z": "0.0"
                    },
                    {
                        "x": "-96.03938",
                        "y": "44.42965",
                        "z": "0.0"
                    },
                    {
                        "x": "-96.048723",
                        "y": "44.429677",
                        "z": "0.0"
                    }
                ]
            }
        ]
    }
}